{
  "a87bbade-7728-43d9-bc23-2538812be3cc": {
    "data": {
      "chain": "Ethereum",
      "project": "merkl",
      "symbol": "USDC",
      "tvlUsd": 1113378463,
      "apyBase": null,
      "apyReward": 1.07058,
      "apy": 1.07058,
      "rewardTokens": [
        "0x58D97B57BB95320F9a05dC918Aef65434969c2B2"
      ],
      "pool": "a87bbade-7728-43d9-bc23-2538812be3cc",
      "apyPct1D": -0.12048,
      "apyPct7D": -0.07885,
      "apyPct30D": null,
      "stablecoin": true,
      "ilRisk": "no",
      "exposure": "single",
      "predictions": {
        "predictedClass": "Stable/Up",
        "predictedProbability": 69,
        "binnedConfidence": 2
      },
      "poolMeta": null,
      "mu": 1.13409,
      "sigma": 0.00442,
      "count": 14,
      "outlier": false,
      "underlyingTokens": [
        "0xA0b86991c6218b36c1d19D4a2e9Eb0cE3606eB48"
      ],
      "il7d": null,
      "apyBase7d": null,
      "apyMean30d": 1.14642,
      "volumeUsd1d": null,
      "volumeUsd7d": null,
      "apyBaseInception": null
    }
  },
  "f981a304-bb6c-45b8-b0c5-fd2f515ad23a": {
    "data": {
      "chain": "Ethereum",
      "project": "aave-v3",
      "symbol": "USDT",
      "tvlUsd": 953483647,
      "apyBase": 4.22207,
      "apyReward": null,
      "apy": 4.22207,
      "rewardTokens": null,
      "pool": "f981a304-bb6c-45b8-b0c5-fd2f515ad23a",
      "apyPct1D": 0.18335,
      "apyPct7D": 0.80672,
      "apyPct30D": 0.08071,
      "stablecoin": true,
      "ilRisk": "no",
      "exposure": "single",
      "predictions": {
        "predictedClass": "Down",
        "predictedProbability": 59,
        "binnedConfidence": 1
      },
      "poolMeta": null,
      "mu": 4.86983,
      "sigma": 0.18865,
      "count": 906,
      "outlier": false,
      "underlyingTokens": [
        "0xdAC17F958D2ee523a2206206994597C13D831ec7"
      ],
      "il7d": null,
      "apyBase7d": null,
      "apyMean30d": 3.67672,
      "volumeUsd1d": null,
      "volumeUsd7d": null,
      "apyBaseInception": null
    }
  }
}